<?xml version="1.0" encoding="utf-8"?>
<extension version="2.5" type="plugin" group="system" method="upgrade">
	<name>PLG_SYSTEM_EXPAUTOSPROFIELDS</name>
	<author>Alexey Kurguz (Grusha)</author>
	<creationDate>04/04/2012</creationDate>
	<copyright>(C) 2005 - 2012 EXP Team. All rights reserved.</copyright>
	<license>Commercial license</license>
	<authorEmail>grushaexp@feellove.eu</authorEmail>
	<authorUrl>www.feellove.eu</authorUrl>
	<version>1.0</version>
	<description>PLG_SYSTEM_EXPAUTOSPROFIELDS_XML_DESCRIPTION</description>	
	<files>
		<folder plugin="expautosprofields">expautosprofields</folder>
		<filename plugin="expautosprofields">expautosprofields.php</filename>
		<folder>language</folder>
	</files>
	<languages>
		<language tag="en-GB">en-GB.plg_system_expautosprofields.ini</language>
		<language tag="en-GB">en-GB.plg_system_expautosprofields.sys.ini</language>
	</languages>
</extension>